[{"Word":"AAH"},{"Word":"AAL"},{"Word":"AAS"},{"Word":"ABA"},{"Word":"ABB"},{"Word":"ABS"},{"Word":"ABY"},{"Word":"ACE"},{"Word":"ACH"},{"Word":"ACT"},{"Word":"ADD"},{"Word":"ADO"},{"Word":"ADS"},{"Word":"ADZ"},{"Word":"AFF"},{"Word":"AFT"},{"Word":"AGA"},{"Word":"AGE"},{"Word":"AGO"},{"Word":"AGS"},{"Word":"AHA"},{"Word":"AHI"},{"Word":"AHS"},{"Word":"AIA"},{"Word":"AID"},{"Word":"AIL"},{"Word":"AIM"},{"Word":"AIN"},{"Word":"AIR"},{"Word":"AIS"},{"Word":"AIT"},{"Word":"AJI"},{"Word":"AKA"},{"Word":"AKE"},{"Word":"ALA"},{"Word":"ALB"},{"Word":"ALE"},{"Word":"ALF"},{"Word":"ALL"},{"Word":"ALP"},{"Word":"ALS"},{"Word":"ALT"},{"Word":"ALU"},{"Word":"AMA"},{"Word":"AME"},{"Word":"AMI"},{"Word":"AMP"},{"Word":"AMU"},{"Word":"ANA"},{"Word":"AND"},{"Word":"ANE"},{"Word":"ANI"},{"Word":"ANN"},{"Word":"ANS"},{"Word":"ANT"},{"Word":"ANY"},{"Word":"APE"},{"Word":"APO"},{"Word":"APP"},{"Word":"APT"},{"Word":"ARB"},{"Word":"ARC"},{"Word":"ARD"},{"Word":"ARE"},{"Word":"ARF"},{"Word":"ARK"},{"Word":"ARM"},{"Word":"ARS"},{"Word":"ART"},{"Word":"ARY"},{"Word":"ASH"},{"Word":"ASK"},{"Word":"ASP"},{"Word":"ASS"},{"Word":"ATE"},{"Word":"ATS"},{"Word":"ATT"},{"Word":"AUA"},{"Word":"AUE"},{"Word":"AUF"},{"Word":"AUK"},{"Word":"AVA"},{"Word":"AVE"},{"Word":"AVO"},{"Word":"AWA"},{"Word":"AWE"},{"Word":"AWK"},{"Word":"AWL"},{"Word":"AWN"},{"Word":"AXE"},{"Word":"AYE"},{"Word":"AYS"},{"Word":"AYU"},{"Word":"AZO"},{"Word":"BAA"},{"Word":"BAC"},{"Word":"BAD"},{"Word":"BAE"},{"Word":"BAG"},{"Word":"BAH"},{"Word":"BAL"},{"Word":"BAM"},{"Word":"BAN"},{"Word":"BAO"},{"Word":"BAP"},{"Word":"BAR"},{"Word":"BAS"},{"Word":"BAT"},{"Word":"BAY"},{"Word":"BED"},{"Word":"BEE"},{"Word":"BEG"},{"Word":"BEL"},{"Word":"BEN"},{"Word":"BES"},{"Word":"BET"},{"Word":"BEY"},{"Word":"BEZ"},{"Word":"BIB"},{"Word":"BID"},{"Word":"BIG"},{"Word":"BIN"},{"Word":"BIO"},{"Word":"BIS"},{"Word":"BIT"},{"Word":"BIZ"},{"Word":"BOA"},{"Word":"BOB"},{"Word":"BOD"},{"Word":"BOG"},{"Word":"BOH"},{"Word":"BOI"},{"Word":"BOK"},{"Word":"BON"},{"Word":"BOO"},{"Word":"BOP"},{"Word":"BOR"},{"Word":"BOS"},{"Word":"BOT"},{"Word":"BOW"},{"Word":"BOX"},{"Word":"BOY"},{"Word":"BRA"},{"Word":"BRO"},{"Word":"BRR"},{"Word":"BRU"},{"Word":"BUB"},{"Word":"BUD"},{"Word":"BUG"},{"Word":"BUM"},{"Word":"BUN"},{"Word":"BUR"},{"Word":"BUS"},{"Word":"BUT"},{"Word":"BUY"},{"Word":"BYE"},{"Word":"BYS"},{"Word":"CAA"},{"Word":"CAB"},{"Word":"CAD"},{"Word":"CAF"},{"Word":"CAG"},{"Word":"CAL"},{"Word":"CAM"},{"Word":"CAN"},{"Word":"CAP"},{"Word":"CAR"},{"Word":"CAT"},{"Word":"CAW"},{"Word":"CAY"},{"Word":"CAZ"},{"Word":"CEE"},{"Word":"CEL"},{"Word":"CEP"},{"Word":"CHA"},{"Word":"CHE"},{"Word":"CHI"},{"Word":"CID"},{"Word":"CIG"},{"Word":"CIS"},{"Word":"CIT"},{"Word":"CLY"},{"Word":"COB"},{"Word":"COD"},{"Word":"COG"},{"Word":"COL"},{"Word":"CON"},{"Word":"COO"},{"Word":"COP"},{"Word":"COR"},{"Word":"COS"},{"Word":"COT"},{"Word":"COW"},{"Word":"COX"},{"Word":"COY"},{"Word":"COZ"},{"Word":"CRU"},{"Word":"CRY"},{"Word":"CUB"},{"Word":"CUD"},{"Word":"CUE"},{"Word":"CUM"},{"Word":"CUP"},{"Word":"CUR"},{"Word":"CUT"},{"Word":"CUZ"},{"Word":"CWM"},{"Word":"DAB"},{"Word":"DAD"},{"Word":"DAE"},{"Word":"DAG"},{"Word":"DAH"},{"Word":"DAK"},{"Word":"DAL"},{"Word":"DAM"},{"Word":"DAN"},{"Word":"DAP"},{"Word":"DAS"},{"Word":"DAW"},{"Word":"DAY"},{"Word":"DEB"},{"Word":"DEE"},{"Word":"DEF"},{"Word":"DEG"},{"Word":"DEI"},{"Word":"DEL"},{"Word":"DEN"},{"Word":"DEP"},{"Word":"DEV"},{"Word":"DEW"},{"Word":"DEX"},{"Word":"DEY"},{"Word":"DIB"},{"Word":"DID"},{"Word":"DIE"},{"Word":"DIF"},{"Word":"DIG"},{"Word":"DIM"},{"Word":"DIN"},{"Word":"DIP"},{"Word":"DIS"},{"Word":"DIT"},{"Word":"DIV"},{"Word":"DOB"},{"Word":"DOC"},{"Word":"DOD"},{"Word":"DOE"},{"Word":"DOF"},{"Word":"DOG"},{"Word":"DOH"},{"Word":"DOL"},{"Word":"DOM"},{"Word":"DON"},{"Word":"DOO"},{"Word":"DOP"},{"Word":"DOR"},{"Word":"DOS"},{"Word":"DOT"},{"Word":"DOW"},{"Word":"DOX"},{"Word":"DOY"},{"Word":"DRY"},{"Word":"DSO"},{"Word":"DUB"},{"Word":"DUD"},{"Word":"DUE"},{"Word":"DUG"},{"Word":"DUH"},{"Word":"DUI"},{"Word":"DUM"},{"Word":"DUN"},{"Word":"DUO"},{"Word":"DUP"},{"Word":"DUX"},{"Word":"DYE"},{"Word":"DZO"},{"Word":"EAN"},{"Word":"EAR"},{"Word":"EAS"},{"Word":"EAT"},{"Word":"EAU"},{"Word":"EBB"},{"Word":"ECH"},{"Word":"ECO"},{"Word":"ECU"},{"Word":"EDH"},{"Word":"EDS"},{"Word":"EEK"},{"Word":"EEL"},{"Word":"EEN"},{"Word":"EEW"},{"Word":"EFF"},{"Word":"EFS"},{"Word":"EFT"},{"Word":"EGG"},{"Word":"EGO"},{"Word":"EHS"},{"Word":"EIK"},{"Word":"EKE"},{"Word":"ELD"},{"Word":"ELF"},{"Word":"ELK"},{"Word":"ELL"},{"Word":"ELM"},{"Word":"ELS"},{"Word":"ELT"},{"Word":"EME"},{"Word":"EMO"},{"Word":"EMS"},{"Word":"EMU"},{"Word":"END"},{"Word":"ENE"},{"Word":"ENG"},{"Word":"ENS"},{"Word":"EON"},{"Word":"ERA"},{"Word":"ERE"},{"Word":"ERF"},{"Word":"ERG"},{"Word":"ERK"},{"Word":"ERM"},{"Word":"ERN"},{"Word":"ERR"},{"Word":"ERS"},{"Word":"ESS"},{"Word":"EST"},{"Word":"ETA"},{"Word":"ETH"},{"Word":"EUK"},{"Word":"EVE"},{"Word":"EVO"},{"Word":"EWE"},{"Word":"EWK"},{"Word":"EWT"},{"Word":"EXO"},{"Word":"EYE"},{"Word":"FAA"},{"Word":"FAB"},{"Word":"FAD"},{"Word":"FAE"},{"Word":"FAG"},{"Word":"FAH"},{"Word":"FAN"},{"Word":"FAP"},{"Word":"FAR"},{"Word":"FAS"},{"Word":"FAT"},{"Word":"FAW"},{"Word":"FAX"},{"Word":"FAY"},{"Word":"FED"},{"Word":"FEE"},{"Word":"FEG"},{"Word":"FEH"},{"Word":"FEM"},{"Word":"FEN"},{"Word":"FER"},{"Word":"FES"},{"Word":"FET"},{"Word":"FEU"},{"Word":"FEW"},{"Word":"FEY"},{"Word":"FEZ"},{"Word":"FIB"},{"Word":"FID"},{"Word":"FIE"},{"Word":"FIG"},{"Word":"FIL"},{"Word":"FIN"},{"Word":"FIR"},{"Word":"FIT"},{"Word":"FIX"},{"Word":"FIZ"},{"Word":"FLU"},{"Word":"FLY"},{"Word":"FOB"},{"Word":"FOE"},{"Word":"FOG"},{"Word":"FOH"},{"Word":"FON"},{"Word":"FOO"},{"Word":"FOP"},{"Word":"FOR"},{"Word":"FOU"},{"Word":"FOX"},{"Word":"FOY"},{"Word":"FRA"},{"Word":"FRO"},{"Word":"FRY"},{"Word":"FUB"},{"Word":"FUD"},{"Word":"FUG"},{"Word":"FUM"},{"Word":"FUN"},{"Word":"FUR"},{"Word":"GAB"},{"Word":"GAD"},{"Word":"GAE"},{"Word":"GAG"},{"Word":"GAK"},{"Word":"GAL"},{"Word":"GAM"},{"Word":"GAN"},{"Word":"GAP"},{"Word":"GAR"},{"Word":"GAS"},{"Word":"GAT"},{"Word":"GAU"},{"Word":"GAW"},{"Word":"GAY"},{"Word":"GED"},{"Word":"GEE"},{"Word":"GEL"},{"Word":"GEM"},{"Word":"GEN"},{"Word":"GEO"},{"Word":"GER"},{"Word":"GET"},{"Word":"GEY"},{"Word":"GHI"},{"Word":"GIB"},{"Word":"GID"},{"Word":"GIE"},{"Word":"GIF"},{"Word":"GIG"},{"Word":"GIN"},{"Word":"GIO"},{"Word":"GIP"},{"Word":"GIS"},{"Word":"GIT"},{"Word":"GJU"},{"Word":"GNU"},{"Word":"GOA"},{"Word":"GOB"},{"Word":"GOD"},{"Word":"GOE"},{"Word":"GON"},{"Word":"GOO"},{"Word":"GOR"},{"Word":"GOS"},{"Word":"GOT"},{"Word":"GOV"},{"Word":"GOX"},{"Word":"GRR"},{"Word":"GUB"},{"Word":"GUE"},{"Word":"GUL"},{"Word":"GUM"},{"Word":"GUN"},{"Word":"GUP"},{"Word":"GUR"},{"Word":"GUS"},{"Word":"GUT"},{"Word":"GUV"},{"Word":"GUY"},{"Word":"GYM"},{"Word":"GYP"},{"Word":"HAD"},{"Word":"HAE"},{"Word":"HAG"},{"Word":"HAH"},{"Word":"HAJ"},{"Word":"HAM"},{"Word":"HAN"},{"Word":"HAO"},{"Word":"HAP"},{"Word":"HAS"},{"Word":"HAT"},{"Word":"HAW"},{"Word":"HAY"},{"Word":"HEH"},{"Word":"HEM"},{"Word":"HEN"},{"Word":"HEP"},{"Word":"HER"},{"Word":"HES"},{"Word":"HET"},{"Word":"HEW"},{"Word":"HEX"},{"Word":"HEY"},{"Word":"HIC"},{"Word":"HID"},{"Word":"HIE"},{"Word":"HIM"},{"Word":"HIN"},{"Word":"HIP"},{"Word":"HIS"},{"Word":"HIT"},{"Word":"HMM"},{"Word":"HOA"},{"Word":"HOB"},{"Word":"HOC"},{"Word":"HOD"},{"Word":"HOE"},{"Word":"HOG"},{"Word":"HOH"},{"Word":"HOI"},{"Word":"HOM"},{"Word":"HON"},{"Word":"HOO"},{"Word":"HOP"},{"Word":"HOS"},{"Word":"HOT"},{"Word":"HOW"},{"Word":"HOX"},{"Word":"HOY"},{"Word":"HUB"},{"Word":"HUE"},{"Word":"HUG"},{"Word":"HUH"},{"Word":"HUI"},{"Word":"HUM"},{"Word":"HUN"},{"Word":"HUP"},{"Word":"HUT"},{"Word":"HYE"},{"Word":"HYP"},{"Word":"ICE"},{"Word":"ICH"},{"Word":"ICK"},{"Word":"ICY"},{"Word":"IDE"},{"Word":"IDS"},{"Word":"IFF"},{"Word":"IFS"},{"Word":"IGG"},{"Word":"ILK"},{"Word":"ILL"},{"Word":"IMP"},{"Word":"ING"},{"Word":"INK"},{"Word":"INN"},{"Word":"INS"},{"Word":"ION"},{"Word":"IOS"},{"Word":"IRE"},{"Word":"IRK"},{"Word":"ISH"},{"Word":"ISM"},{"Word":"ISO"},{"Word":"ITA"},{"Word":"ITS"},{"Word":"IVY"},{"Word":"IWI"},{"Word":"JAB"},{"Word":"JAG"},{"Word":"JAI"},{"Word":"JAK"},{"Word":"JAM"},{"Word":"JAP"},{"Word":"JAR"},{"Word":"JAW"},{"Word":"JAY"},{"Word":"JEE"},{"Word":"JET"},{"Word":"JEU"},{"Word":"JIB"},{"Word":"JIG"},{"Word":"JIN"},{"Word":"JIZ"},{"Word":"JOB"},{"Word":"JOE"},{"Word":"JOG"},{"Word":"JOL"},{"Word":"JOR"},{"Word":"JOT"},{"Word":"JOW"},{"Word":"JOY"},{"Word":"JUD"},{"Word":"JUG"},{"Word":"JUN"},{"Word":"JUS"},{"Word":"JUT"},{"Word":"KAB"},{"Word":"KAE"},{"Word":"KAF"},{"Word":"KAI"},{"Word":"KAK"},{"Word":"KAM"},{"Word":"KAS"},{"Word":"KAT"},{"Word":"KAW"},{"Word":"KAY"},{"Word":"KEA"},{"Word":"KEB"},{"Word":"KED"},{"Word":"KEF"},{"Word":"KEG"},{"Word":"KEN"},{"Word":"KEP"},{"Word":"KET"},{"Word":"KEX"},{"Word":"KEY"},{"Word":"KHI"},{"Word":"KID"},{"Word":"KIF"},{"Word":"KIN"},{"Word":"KIP"},{"Word":"KIR"},{"Word":"KIS"},{"Word":"KIT"},{"Word":"KOA"},{"Word":"KOB"},{"Word":"KOI"},{"Word":"KON"},{"Word":"KOP"},{"Word":"KOR"},{"Word":"KOS"},{"Word":"KOW"},{"Word":"KUE"},{"Word":"KYE"},{"Word":"KYU"},{"Word":"LAB"},{"Word":"LAC"},{"Word":"LAD"},{"Word":"LAG"},{"Word":"LAH"},{"Word":"LAM"},{"Word":"LAP"},{"Word":"LAR"},{"Word":"LAS"},{"Word":"LAT"},{"Word":"LAV"},{"Word":"LAW"},{"Word":"LAX"},{"Word":"LAY"},{"Word":"LEA"},{"Word":"LED"},{"Word":"LEE"},{"Word":"LEG"},{"Word":"LEI"},{"Word":"LEK"},{"Word":"LEP"},{"Word":"LET"},{"Word":"LEU"},{"Word":"LEV"},{"Word":"LEW"},{"Word":"LEX"},{"Word":"LEY"},{"Word":"LIB"},{"Word":"LID"},{"Word":"LIE"},{"Word":"LIG"},{"Word":"LIN"},{"Word":"LIP"},{"Word":"LIS"},{"Word":"LIT"},{"Word":"LOB"},{"Word":"LOD"},{"Word":"LOG"},{"Word":"LOO"},{"Word":"LOP"},{"Word":"LOR"},{"Word":"LOS"},{"Word":"LOT"},{"Word":"LOU"},{"Word":"LOW"},{"Word":"LOX"},{"Word":"LOY"},{"Word":"LUD"},{"Word":"LUG"},{"Word":"LUM"},{"Word":"LUN"},{"Word":"LUR"},{"Word":"LUV"},{"Word":"LUX"},{"Word":"LUZ"},{"Word":"LYE"},{"Word":"LYM"},{"Word":"MAA"},{"Word":"MAC"},{"Word":"MAD"},{"Word":"MAE"},{"Word":"MAG"},{"Word":"MAK"},{"Word":"MAL"},{"Word":"MAM"},{"Word":"MAN"},{"Word":"MAP"},{"Word":"MAR"},{"Word":"MAS"},{"Word":"MAT"},{"Word":"MAW"},{"Word":"MAX"},{"Word":"MAY"},{"Word":"MED"},{"Word":"MEE"},{"Word":"MEG"},{"Word":"MEH"},{"Word":"MEL"},{"Word":"MEM"},{"Word":"MEN"},{"Word":"MES"},{"Word":"MET"},{"Word":"MEU"},{"Word":"MEW"},{"Word":"MHO"},{"Word":"MIB"},{"Word":"MIC"},{"Word":"MID"},{"Word":"MIG"},{"Word":"MIL"},{"Word":"MIM"},{"Word":"MIR"},{"Word":"MIS"},{"Word":"MIX"},{"Word":"MIZ"},{"Word":"MMM"},{"Word":"MNA"},{"Word":"MOA"},{"Word":"MOB"},{"Word":"MOC"},{"Word":"MOD"},{"Word":"MOE"},{"Word":"MOG"},{"Word":"MOI"},{"Word":"MOL"},{"Word":"MOM"},{"Word":"MON"},{"Word":"MOO"},{"Word":"MOP"},{"Word":"MOR"},{"Word":"MOS"},{"Word":"MOT"},{"Word":"MOU"},{"Word":"MOW"},{"Word":"MOY"},{"Word":"MOZ"},{"Word":"MUD"},{"Word":"MUG"},{"Word":"MUM"},{"Word":"MUN"},{"Word":"MUS"},{"Word":"MUT"},{"Word":"MUX"},{"Word":"MYC"},{"Word":"NAB"},{"Word":"NAE"},{"Word":"NAG"},{"Word":"NAH"},{"Word":"NAM"},{"Word":"NAN"},{"Word":"NAP"},{"Word":"NAS"},{"Word":"NAT"},{"Word":"NAV"},{"Word":"NAW"},{"Word":"NAY"},{"Word":"NEB"},{"Word":"NED"},{"Word":"NEE"},{"Word":"NEF"},{"Word":"NEG"},{"Word":"NEK"},{"Word":"NEP"},{"Word":"NET"},{"Word":"NEW"},{"Word":"NIB"},{"Word":"NID"},{"Word":"NIE"},{"Word":"NIL"},{"Word":"NIM"},{"Word":"NIP"},{"Word":"NIS"},{"Word":"NIT"},{"Word":"NIX"},{"Word":"NOB"},{"Word":"NOD"},{"Word":"NOG"},{"Word":"NOH"},{"Word":"NOM"},{"Word":"NON"},{"Word":"NOO"},{"Word":"NOR"},{"Word":"NOS"},{"Word":"NOT"},{"Word":"NOW"},{"Word":"NOX"},{"Word":"NOY"},{"Word":"NTH"},{"Word":"NUB"},{"Word":"NUG"},{"Word":"NUN"},{"Word":"NUR"},{"Word":"NUS"},{"Word":"NUT"},{"Word":"NYE"},{"Word":"NYM"},{"Word":"NYS"},{"Word":"OAF"},{"Word":"OAK"},{"Word":"OAR"},{"Word":"OAT"},{"Word":"OBA"},{"Word":"OBE"},{"Word":"OBI"},{"Word":"OBO"},{"Word":"OBS"},{"Word":"OCA"},{"Word":"OCH"},{"Word":"ODA"},{"Word":"ODD"},{"Word":"ODE"},{"Word":"ODS"},{"Word":"OES"},{"Word":"OFF"},{"Word":"OFT"},{"Word":"OHM"},{"Word":"OHO"},{"Word":"OHS"},{"Word":"OIK"},{"Word":"OIL"},{"Word":"OIS"},{"Word":"OKA"},{"Word":"OKE"},{"Word":"OLD"},{"Word":"OLE"},{"Word":"OLM"},{"Word":"OMA"},{"Word":"OMS"},{"Word":"ONE"},{"Word":"ONO"},{"Word":"ONS"},{"Word":"ONY"},{"Word":"OOF"},{"Word":"OOH"},{"Word":"OOM"},{"Word":"OON"},{"Word":"OOP"},{"Word":"OOR"},{"Word":"OOS"},{"Word":"OOT"},{"Word":"OPA"},{"Word":"OPE"},{"Word":"OPS"},{"Word":"OPT"},{"Word":"ORA"},{"Word":"ORB"},{"Word":"ORC"},{"Word":"ORD"},{"Word":"ORE"},{"Word":"ORF"},{"Word":"ORG"},{"Word":"ORS"},{"Word":"ORT"},{"Word":"OSE"},{"Word":"OUD"},{"Word":"OUK"},{"Word":"OUP"},{"Word":"OUR"},{"Word":"OUS"},{"Word":"OUT"},{"Word":"OVA"},{"Word":"OWE"},{"Word":"OWL"},{"Word":"OWN"},{"Word":"OWT"},{"Word":"OXO"},{"Word":"OXY"},{"Word":"OYE"},{"Word":"OYS"},{"Word":"PAC"},{"Word":"PAD"},{"Word":"PAH"},{"Word":"PAK"},{"Word":"PAL"},{"Word":"PAM"},{"Word":"PAN"},{"Word":"PAP"},{"Word":"PAR"},{"Word":"PAS"},{"Word":"PAT"},{"Word":"PAV"},{"Word":"PAW"},{"Word":"PAX"},{"Word":"PAY"},{"Word":"PEA"},{"Word":"PEC"},{"Word":"PED"},{"Word":"PEE"},{"Word":"PEG"},{"Word":"PEH"},{"Word":"PEL"},{"Word":"PEN"},{"Word":"PEP"},{"Word":"PER"},{"Word":"PES"},{"Word":"PET"},{"Word":"PEW"},{"Word":"PHI"},{"Word":"PHO"},{"Word":"PHT"},{"Word":"PIA"},{"Word":"PIC"},{"Word":"PIE"},{"Word":"PIG"},{"Word":"PIN"},{"Word":"PIP"},{"Word":"PIR"},{"Word":"PIS"},{"Word":"PIT"},{"Word":"PIU"},{"Word":"PIX"},{"Word":"PLU"},{"Word":"PLY"},{"Word":"POA"},{"Word":"POD"},{"Word":"POH"},{"Word":"POI"},{"Word":"POL"},{"Word":"POM"},{"Word":"POO"},{"Word":"POP"},{"Word":"POS"},{"Word":"POT"},{"Word":"POW"},{"Word":"POX"},{"Word":"POZ"},{"Word":"PRE"},{"Word":"PRO"},{"Word":"PRY"},{"Word":"PSI"},{"Word":"PST"},{"Word":"PUB"},{"Word":"PUD"},{"Word":"PUG"},{"Word":"PUH"},{"Word":"PUL"},{"Word":"PUN"},{"Word":"PUP"},{"Word":"PUR"},{"Word":"PUS"},{"Word":"PUT"},{"Word":"PUY"},{"Word":"PWN"},{"Word":"PYA"},{"Word":"PYE"},{"Word":"PYX"},{"Word":"QAT"},{"Word":"QIN"},{"Word":"QIS"},{"Word":"QUA"},{"Word":"RAD"},{"Word":"RAG"},{"Word":"RAH"},{"Word":"RAI"},{"Word":"RAJ"},{"Word":"RAM"},{"Word":"RAN"},{"Word":"RAP"},{"Word":"RAS"},{"Word":"RAT"},{"Word":"RAV"},{"Word":"RAW"},{"Word":"RAX"},{"Word":"RAY"},{"Word":"REB"},{"Word":"REC"},{"Word":"RED"},{"Word":"REE"},{"Word":"REF"},{"Word":"REG"},{"Word":"REH"},{"Word":"REI"},{"Word":"REM"},{"Word":"REN"},{"Word":"REO"},{"Word":"REP"},{"Word":"RES"},{"Word":"RET"},{"Word":"REV"},{"Word":"REW"},{"Word":"REX"},{"Word":"REZ"},{"Word":"RHO"},{"Word":"RHY"},{"Word":"RIA"},{"Word":"RIB"},{"Word":"RID"},{"Word":"RIF"},{"Word":"RIG"},{"Word":"RIM"},{"Word":"RIN"},{"Word":"RIP"},{"Word":"RIT"},{"Word":"RIZ"},{"Word":"ROB"},{"Word":"ROC"},{"Word":"ROD"},{"Word":"ROE"},{"Word":"ROK"},{"Word":"ROM"},{"Word":"ROO"},{"Word":"ROT"},{"Word":"ROW"},{"Word":"RUB"},{"Word":"RUC"},{"Word":"RUD"},{"Word":"RUE"},{"Word":"RUG"},{"Word":"RUM"},{"Word":"RUN"},{"Word":"RUT"},{"Word":"RYA"},{"Word":"RYE"},{"Word":"RYU"},{"Word":"SAB"},{"Word":"SAC"},{"Word":"SAD"},{"Word":"SAE"},{"Word":"SAG"},{"Word":"SAI"},{"Word":"SAL"},{"Word":"SAM"},{"Word":"SAN"},{"Word":"SAP"},{"Word":"SAR"},{"Word":"SAT"},{"Word":"SAU"},{"Word":"SAV"},{"Word":"SAW"},{"Word":"SAX"},{"Word":"SAY"},{"Word":"SAZ"},{"Word":"SEA"},{"Word":"SEC"},{"Word":"SED"},{"Word":"SEE"},{"Word":"SEG"},{"Word":"SEI"},{"Word":"SEL"},{"Word":"SEN"},{"Word":"SER"},{"Word":"SET"},{"Word":"SEV"},{"Word":"SEW"},{"Word":"SEX"},{"Word":"SEY"},{"Word":"SEZ"},{"Word":"SHA"},{"Word":"SHE"},{"Word":"SHH"},{"Word":"SHO"},{"Word":"SHY"},{"Word":"SIB"},{"Word":"SIC"},{"Word":"SIF"},{"Word":"SIG"},{"Word":"SIK"},{"Word":"SIM"},{"Word":"SIN"},{"Word":"SIP"},{"Word":"SIR"},{"Word":"SIS"},{"Word":"SIT"},{"Word":"SIX"},{"Word":"SKA"},{"Word":"SKI"},{"Word":"SKY"},{"Word":"SLY"},{"Word":"SMA"},{"Word":"SNY"},{"Word":"SOB"},{"Word":"SOC"},{"Word":"SOD"},{"Word":"SOG"},{"Word":"SOH"},{"Word":"SOL"},{"Word":"SOM"},{"Word":"SON"},{"Word":"SOP"},{"Word":"SOS"},{"Word":"SOT"},{"Word":"SOU"},{"Word":"SOV"},{"Word":"SOW"},{"Word":"SOX"},{"Word":"SOY"},{"Word":"SOZ"},{"Word":"SPA"},{"Word":"SPY"},{"Word":"SRI"},{"Word":"STY"},{"Word":"SUB"},{"Word":"SUD"},{"Word":"SUE"},{"Word":"SUG"},{"Word":"SUI"},{"Word":"SUK"},{"Word":"SUM"},{"Word":"SUN"},{"Word":"SUP"},{"Word":"SUQ"},{"Word":"SUR"},{"Word":"SUS"},{"Word":"SWY"},{"Word":"SYE"},{"Word":"SYN"},{"Word":"TAB"},{"Word":"TAD"},{"Word":"TAE"},{"Word":"TAG"},{"Word":"TAI"},{"Word":"TAJ"},{"Word":"TAK"},{"Word":"TAM"},{"Word":"TAN"},{"Word":"TAO"},{"Word":"TAP"},{"Word":"TAR"},{"Word":"TAS"},{"Word":"TAT"},{"Word":"TAU"},{"Word":"TAV"},{"Word":"TAW"},{"Word":"TAX"},{"Word":"TAY"},{"Word":"TEA"},{"Word":"TEC"},{"Word":"TED"},{"Word":"TEE"},{"Word":"TEF"},{"Word":"TEG"},{"Word":"TEL"},{"Word":"TEN"},{"Word":"TES"},{"Word":"TET"},{"Word":"TEW"},{"Word":"TEX"},{"Word":"THE"},{"Word":"THO"},{"Word":"THY"},{"Word":"TIC"},{"Word":"TID"},{"Word":"TIE"},{"Word":"TIG"},{"Word":"TIK"},{"Word":"TIL"},{"Word":"TIN"},{"Word":"TIP"},{"Word":"TIS"},{"Word":"TIT"},{"Word":"TIX"},{"Word":"TIZ"},{"Word":"TOC"},{"Word":"TOD"},{"Word":"TOE"},{"Word":"TOG"},{"Word":"TOM"},{"Word":"TON"},{"Word":"TOO"},{"Word":"TOP"},{"Word":"TOR"},{"Word":"TOT"},{"Word":"TOW"},{"Word":"TOY"},{"Word":"TRY"},{"Word":"TSK"},{"Word":"TUB"},{"Word":"TUG"},{"Word":"TUI"},{"Word":"TUM"},{"Word":"TUN"},{"Word":"TUP"},{"Word":"TUT"},{"Word":"TUX"},{"Word":"TWA"},{"Word":"TWO"},{"Word":"TWP"},{"Word":"TYE"},{"Word":"TYG"},{"Word":"UDO"},{"Word":"UDS"},{"Word":"UEY"},{"Word":"UFO"},{"Word":"UGH"},{"Word":"UGS"},{"Word":"UKE"},{"Word":"ULE"},{"Word":"ULU"},{"Word":"UME"},{"Word":"UMM"},{"Word":"UMP"},{"Word":"UMS"},{"Word":"UMU"},{"Word":"UNI"},{"Word":"UNS"},{"Word":"UPO"},{"Word":"UPS"},{"Word":"URB"},{"Word":"URD"},{"Word":"URE"},{"Word":"URN"},{"Word":"URP"},{"Word":"USE"},{"Word":"UTA"},{"Word":"UTE"},{"Word":"UTS"},{"Word":"UTU"},{"Word":"UVA"},{"Word":"VAC"},{"Word":"VAE"},{"Word":"VAG"},{"Word":"VAN"},{"Word":"VAR"},{"Word":"VAS"},{"Word":"VAT"},{"Word":"VAU"},{"Word":"VAV"},{"Word":"VAW"},{"Word":"VAX"},{"Word":"VEE"},{"Word":"VEG"},{"Word":"VET"},{"Word":"VEX"},{"Word":"VIA"},{"Word":"VID"},{"Word":"VIE"},{"Word":"VIG"},{"Word":"VIM"},{"Word":"VIN"},{"Word":"VIS"},{"Word":"VLY"},{"Word":"VOE"},{"Word":"VOG"},{"Word":"VOL"},{"Word":"VOM"},{"Word":"VOR"},{"Word":"VOW"},{"Word":"VOX"},{"Word":"VUG"},{"Word":"VUM"},{"Word":"WAB"},{"Word":"WAD"},{"Word":"WAE"},{"Word":"WAG"},{"Word":"WAI"},{"Word":"WAN"},{"Word":"WAP"},{"Word":"WAR"},{"Word":"WAS"},{"Word":"WAT"},{"Word":"WAW"},{"Word":"WAX"},{"Word":"WAY"},{"Word":"WAZ"},{"Word":"WEB"},{"Word":"WED"},{"Word":"WEE"},{"Word":"WEM"},{"Word":"WEN"},{"Word":"WET"},{"Word":"WEX"},{"Word":"WEY"},{"Word":"WHA"},{"Word":"WHO"},{"Word":"WHY"},{"Word":"WIG"},{"Word":"WIN"},{"Word":"WIS"},{"Word":"WIT"},{"Word":"WIZ"},{"Word":"WOE"},{"Word":"WOF"},{"Word":"WOK"},{"Word":"WON"},{"Word":"WOO"},{"Word":"WOP"},{"Word":"WOS"},{"Word":"WOT"},{"Word":"WOW"},{"Word":"WOX"},{"Word":"WRY"},{"Word":"WUD"},{"Word":"WUS"},{"Word":"WUZ"},{"Word":"WYE"},{"Word":"WYN"},{"Word":"XED"},{"Word":"XIS"},{"Word":"YAD"},{"Word":"YAE"},{"Word":"YAG"},{"Word":"YAH"},{"Word":"YAK"},{"Word":"YAM"},{"Word":"YAP"},{"Word":"YAR"},{"Word":"YAS"},{"Word":"YAW"},{"Word":"YAY"},{"Word":"YEA"},{"Word":"YEH"},{"Word":"YEN"},{"Word":"YEP"},{"Word":"YER"},{"Word":"YES"},{"Word":"YET"},{"Word":"YEW"},{"Word":"YEX"},{"Word":"YEZ"},{"Word":"YGO"},{"Word":"YIN"},{"Word":"YIP"},{"Word":"YOB"},{"Word":"YOD"},{"Word":"YOK"},{"Word":"YOM"},{"Word":"YON"},{"Word":"YOU"},{"Word":"YOW"},{"Word":"YUG"},{"Word":"YUK"},{"Word":"YUM"},{"Word":"YUP"},{"Word":"YUS"},{"Word":"ZAG"},{"Word":"ZAP"},{"Word":"ZAS"},{"Word":"ZAX"},{"Word":"ZEA"},{"Word":"ZED"},{"Word":"ZEE"},{"Word":"ZEK"},{"Word":"ZEL"},{"Word":"ZEN"},{"Word":"ZEP"},{"Word":"ZEX"},{"Word":"ZHO"},{"Word":"ZIG"},{"Word":"ZIN"},{"Word":"ZIP"},{"Word":"ZIT"},{"Word":"ZIZ"},{"Word":"ZOA"},{"Word":"ZOL"},{"Word":"ZOO"},{"Word":"ZOS"},{"Word":"ZUZ"},{"Word":"ZZZ"}]